{
    "identifier": "cobblemon:national_hoenn",
    "pokemon_list": [
        {
            "identifier": "cobblemon:treecko"
        },
        {
            "identifier": "cobblemon:grovyle"
        },
        {
            "identifier": "cobblemon:sceptile"
        },
        {
            "identifier": "cobblemon:torchic"
        },
        {
            "identifier": "cobblemon:combusken"
        },
        {
            "identifier": "cobblemon:blaziken"
        },
        {
            "identifier": "cobblemon:mudkip"
        },
        {
            "identifier": "cobblemon:marshtomp"
        },
        {
            "identifier": "cobblemon:swampert"
        },
        {
            "identifier": "cobblemon:poochyena"
        },
        {
            "identifier": "cobblemon:mightyena"
        },
        {
            "identifier": "cobblemon:zigzagoon",
            "forms": [
                "normal",
                "galarian"
            ]
        },
        {
            "identifier": "cobblemon:linoone",
            "forms": [
                "normal",
                "galarian"
            ]
        },
        {
            "identifier": "cobblemon:lotad"
        },
        {
            "identifier": "cobblemon:lombre"
        },
        {
            "identifier": "cobblemon:ludicolo"
        },
        {
            "identifier": "cobblemon:seedot"
        },
        {
            "identifier": "cobblemon:nuzleaf"
        },
        {
            "identifier": "cobblemon:shiftry"
        },
        {
            "identifier": "cobblemon:taillow"
        },
        {
            "identifier": "cobblemon:swellow"
        },
        {
            "identifier": "cobblemon:wingull"
        },
        {
            "identifier": "cobblemon:pelipper"
        },
        {
            "identifier": "cobblemon:ralts"
        },
        {
            "identifier": "cobblemon:kirlia"
        },
        {
            "identifier": "cobblemon:gardevoir"
        },
        {
            "identifier": "cobblemon:surskit"
        },
        {
            "identifier": "cobblemon:masquerain"
        },
        {
            "identifier": "cobblemon:shroomish"
        },
        {
            "identifier": "cobblemon:breloom"
        },
        {
            "identifier": "cobblemon:nincada"
        },
        {
            "identifier": "cobblemon:ninjask"
        },
        {
            "identifier": "cobblemon:shedinja"
        },
        {
            "identifier": "cobblemon:whismur"
        },
        {
            "identifier": "cobblemon:loudred"
        },
        {
            "identifier": "cobblemon:exploud"
        },
        {
            "identifier": "cobblemon:makuhita"
        },
        {
            "identifier": "cobblemon:hariyama"
        },
        {
            "identifier": "cobblemon:nosepass"
        },
        {
            "identifier": "cobblemon:sableye"
        },
        {
            "identifier": "cobblemon:mawile"
        },
        {
            "identifier": "cobblemon:aron"
        },
        {
            "identifier": "cobblemon:lairon"
        },
        {
            "identifier": "cobblemon:aggron"
        },
        {
            "identifier": "cobblemon:plusle"
        },
        {
            "identifier": "cobblemon:minun"
        },
        {
            "identifier": "cobblemon:volbeat"
        },
        {
            "identifier": "cobblemon:illumise"
        },
        {
            "identifier": "cobblemon:roselia"
        },
        {
            "identifier": "cobblemon:carvanha"
        },
        {
            "identifier": "cobblemon:sharpedo"
        },
        {
            "identifier": "cobblemon:wailmer"
        },
        {
            "identifier": "cobblemon:wailord"
        },
        {
            "identifier": "cobblemon:numel"
        },
        {
            "identifier": "cobblemon:camerupt"
        },
        {
            "identifier": "cobblemon:torkoal"
        },
        {
            "identifier": "cobblemon:spinda",
            "forms": [
                "normal",
                "face-spots-none",
                "face-spots-1",
                "face-spots-2",
                "face-spots-3",
                "face-spots-4",
                "face-spots-5",
                "face-spots-6",
                "face-spots-7",
                "face-spots-8",
                "face-spots-9",
                "face-spots-10",
                "face-spots-11",
                "face-spots2-none",
                "face-spots2-1",
                "face-spots2-2",
                "face-spots2-3",
                "face-spots2-4",
                "face-spots2-5",
                "face-spots2-6",
                "face-spots2-7",
                "face-spots2-8",
                "face-spots2-9",
                "face-spots2-10",
                "face-spots2-11",
                "left-ear-spots-none",
                "left-ear-spots-1",
                "left-ear-spots-2",
                "left-ear-spots-3",
                "left-ear-spots-4",
                "left-ear-spots-5",
                "left-ear-spots-6",
                "right-ear-spots-none",
                "right-ear-spots-1",
                "right-ear-spots-2",
                "right-ear-spots-3",
                "right-ear-spots-4",
                "right-ear-spots-5",
                "right-ear-spots-6",
                "special-spots-1",
                "special-spots-2",
                "special-spots-3",
                "special-spots-4"
            ]
        },
        {
            "identifier": "cobblemon:trapinch"
        },
        {
            "identifier": "cobblemon:vibrava"
        },
        {
            "identifier": "cobblemon:flygon"
        },
        {
            "identifier": "cobblemon:cacnea"
        },
        {
            "identifier": "cobblemon:cacturne"
        },
        {
            "identifier": "cobblemon:lunatone"
        },
        {
            "identifier": "cobblemon:solrock"
        },
        {
            "identifier": "cobblemon:barboach"
        },
        {
            "identifier": "cobblemon:whiscash"
        },
        {
            "identifier": "cobblemon:baltoy"
        },
        {
            "identifier": "cobblemon:claydol"
        },
        {
            "identifier": "cobblemon:lileep"
        },
        {
            "identifier": "cobblemon:cradily"
        },
        {
            "identifier": "cobblemon:anorith"
        },
        {
            "identifier": "cobblemon:armaldo"
        },
        {
            "identifier": "cobblemon:duskull"
        },
        {
            "identifier": "cobblemon:dusclops"
        },
        {
            "identifier": "cobblemon:tropius"
        },
        {
            "identifier": "cobblemon:chimecho"
        },
        {
            "identifier": "cobblemon:clamperl"
        },
        {
            "identifier": "cobblemon:huntail"
        },
        {
            "identifier": "cobblemon:gorebyss"
        },
        {
            "identifier": "cobblemon:relicanth"
        },
        {
            "identifier": "cobblemon:luvdisc"
        },
        {
            "identifier": "cobblemon:beldum"
        },
        {
            "identifier": "cobblemon:metang"
        },
        {
            "identifier": "cobblemon:metagross"
        },
        {
            "identifier": "cobblemon:rayquaza"
        }
    ]
}