{
    "name": "ferrothorn",
    "nationalPokedexNumber": 598,
    "primaryType": "grass",
    "secondaryType": "steel",
    "abilities": [
        "ironbarbs",
        "h:anticipation"
    ],
    "baseStats": {
        "hp": 74,
        "attack": 94,
        "defence": 131,
        "special_attack": 54,
        "special_defence": 116,
        "speed": 20
    },
    "catchRate": 90,
    "maleRatio": 0.5,
    "shoulderMountable": false,
    "forms": [],
    "baseExperienceYield": 171,
    "experienceGroup": "mediumfast",
    "eggCycles": 20,
    "eggGroups": [
        "plant",
        "mineral"
    ],
    "moves": [
        "0:powerwhip",
        "1:tackle",
        "1:pinmissile",
        "1:harden",
        "1:metalclaw",
        "15:ingrain",
        "20:flashcannon",
        "25:ironhead",
        "30:selfdestruct",
        "35:irondefense",
        "43:curse",
        "49:gyroball",
        "56:explosion",
        "tm:assurance",
        "tm:attract",
        "tm:bodypress",
        "tm:brutalswing",
        "tm:bulldoze",
        "tm:bulletseed",
        "tm:endure",
        "tm:energyball",
        "tm:facade",
        "tm:gigadrain",
        "tm:gigaimpact",
        "tm:grassknot",
        "tm:heavyslam",
        "tm:hyperbeam",
        "tm:payback",
        "tm:poisonjab",
        "tm:protect",
        "tm:rest",
        "tm:revenge",
        "tm:round",
        "tm:sandstorm",
        "tm:seedbomb",
        "tm:shadowclaw",
        "tm:sleeptalk",
        "tm:snore",
        "tm:solarbeam",
        "tm:spikes",
        "tm:stealthrock",
        "tm:substitute",
        "tm:sunnyday",
        "tm:swordsdance",
        "tm:thunder",
        "tm:thunderbolt",
        "tm:thunderwave",
        "tutor:steelbeam",
        "tutor:steelroller"
    ],
    "labels": [
        "gen5"
    ],
    "pokedex": [
        "pokemod.species.ferrothorn.desc1",
        "pokemod.species.ferrothorn.desc2"
    ],
    "preEvolution": "ferroseed",
    "evolutions": [],
    "baseScale": 1.0,
    "hitbox": {
        "width": 1.0,
        "height": 1.0,
        "fixed": false
    }
}