{
    "type": "minecraft:crafting_shapeless",
    "ingredients": [
        {
            "item": "cobblemon:medicinal_brew"
        },
        {
            "item": "minecraft:wheat"
        },
        {
            "item": "minecraft:wheat"
        },
        {
            "item": "cobblemon:tamato_berry"
        },
        {
            "item": "cobblemon:tamato_berry"
        },
        {
            "item": "cobblemon:green_mint_leaf"
        },
        {
            "item": "cobblemon:green_mint_leaf"
        }
    ],
    "result": {
        "id": "cobblemon:carbos"
    }
}