{
    "name": "glalie",
    "nationalPokedexNumber": 362,
    "primaryType": "ice",
    "abilities": [
        "innerfocus",
        "icebody",
        "h:moody"
    ],
    "baseStats": {
        "hp": 80,
        "attack": 80,
        "defence": 80,
        "special_attack": 80,
        "special_defence": 80,
        "speed": 80
    },
    "catchRate": 75,
    "maleRatio": 0.5,
    "shoulderMountable": false,
    "forms": [
        {
            "name": "mega",
            "abilities": [
                "refrigerate"
            ],
            "baseStats": {
                "hp": 80,
                "attack": 120,
                "defence": 80,
                "special_attack": 120,
                "special_defence": 80,
                "speed": 100
            },
            "aspects": [
                "mega"
            ]
        }
    ],
    "baseExperienceYield": 168,
    "experienceGroup": "mediumfast",
    "eggCycles": 20,
    "eggGroups": [
        "fairy",
        "mineral"
    ],
    "moves": [
        "0:freezedry",
        "1:leer",
        "1:doubleteam",
        "1:powdersnow",
        "1:astonish",
        "1:sheercold",
        "15:iceshard",
        "20:protect",
        "25:icywind",
        "30:frostbreath",
        "35:bite",
        "40:icefang",
        "47:hail",
        "54:headbutt",
        "61:crunch",
        "68:blizzard",
        "tm:attract",
        "tm:avalanche",
        "tm:bodyslam",
        "tm:bulldoze",
        "tm:darkpulse",
        "tm:earthquake",
        "tm:endure",
        "tm:facade",
        "tm:faketears",
        "tm:gigaimpact",
        "tm:gyroball",
        "tm:hex",
        "tm:hyperbeam",
        "tm:icebeam",
        "tm:iciclespear",
        "tm:ironhead",
        "tm:lightscreen",
        "tm:payback",
        "tm:raindance",
        "tm:rest",
        "tm:round",
        "tm:safeguard",
        "tm:scaryface",
        "tm:selfdestruct",
        "tm:shadowball",
        "tm:sleeptalk",
        "tm:snore",
        "tm:spikes",
        "tm:substitute",
        "tm:taunt",
        "tm:weatherball",
        "tutor:steelroller"
    ],
    "labels": [
        "gen3"
    ],
    "pokedex": [
        "pokemod.species.glalie.desc1",
        "pokemod.species.glalie.desc2"
    ],
    "preEvolution": "snorunt",
    "evolutions": [],
    "baseScale": 1.0,
    "hitbox": {
        "width": 1.0,
        "height": 1.0,
        "fixed": false
    }
}