{
    "id": "0001-bulbasaur",
    "version": "1",
    "neededInstalledMods": [],
    "neededUninstalledMods": [],
    "spawns": [
        {
            "id": "bulbasaur",
            "pokemon": "bulbasaur",
            "type": "pokemon",
            "context": "grounded",
            "bucket": "ultra-rare",
            "level": "5-15",
            "weight": 7.0,
            "condition": {
                "canSeeSky": true,
                "biomes": [
                    "#minecraft:is_jungle"
                ],
                "timeRange": "day"
            }
        }
    ]
}