{
  "display": {
    "icon": {
      "item": "cobblemon:healing_machine"
    },
    "title": {
      "translate": "advancements.cobblemon.healing_machine"
    },
    "description": {
      "translate": "advancements.cobblemon.healing_machine.description"
    },
    "frame": "task"
  },
  "parent": "cobblemon:craft_poke_ball",
  "criteria": {
    "heal": {
      "trigger": "minecraft:location",
      "conditions": {
        "player": [
          {
            "condition": "minecraft:entity_properties",
            "entity": "this",
            "predicate": {
              "location": {
                "block": {
                  "blocks": [
                    "cobblemon:healing_machine"
                  ],
                  "state": {
                    "charge": 6
                  }
                }
              }
            }
          }
        ]
      }
    }
  },
  "sends_telemetry_event": false
}
